Workbook
Name Slicer_Brand: #N/A
Name Slicer_Category: #N/A
Name Slicer_City: #N/A
Name Slicer_Delivery_Status: #N/A
Name Slicer_Months__Order_Date2: #N/A
Name Slicer_Payment_Mode: #N/A
Name Slicer_Product: #N/A
Name Slicer_Product1: #N/A
Name Slicer_Return_Status: #N/A
Name Slicer_Seller: #N/A
Name Slicer_State: #N/A

Sheet Dashboard

Sheet Order Data
A1: Order ID | B1: Order Date | C1: Customer Name | D1: City | E1: State | F1: Category | G1: Product | H1: Brand | I1: Seller | J1: Quantity | K1: Unit Price | L1: Discount | M1: Revenue | N1: Profit | O1: Payment Mode | P1: Delivery Status | Q1: Rating | R1: Return Status
A2: OD1796990001 | B2: 45782 | C2: Shilpa Shetty | D2: Chennai | E2: Tamil Nadu | F2: Electronics | G2: Wireless Earbuds | H2: boAt | I2: RetailNet | J2: 4 | K2: 40597 | L2: 0.2 | M2: =J2*K2*(1-L2) -> 129910.4 | N2: =M2*0.21 -> 27281.184 | O2: Credit Card | P2: Delivered | Q2: 5 | R2: No Return
A3: OD2267880002 | B3: 46060 | C3: Rohan Das | D3: Chennai | E3: Tamil Nadu | F3: Beauty & Grooming | G3: Face Wash | H3: Nivea | I3: RetailNet | J3: 4 | K3: 546 | L3: 0.2 | M3: =J3*K3*(1-L3) -> 1747.2 | N3: =M3*0.21 -> 366.912 | O3: Debit Card | P3: Delivered | Q3: 3 | R3: No Return
A4: OD3554840003 | B4: 46031 | C4: Ananya Iyer | D4: Kolkata | E4: West Bengal | F4: Electronics | G4: Smartphone | H4: Realme | I4: RetailNet | J4: 2 | K4: 17147 | L4: 0.05 | M4: =J4*K4*(1-L4) -> 32579.3 | N4: =M4*0.23 -> 7493.239 | O4: Debit Card | P4: Delivered | Q4: 3 | R4: No Return | T4: =AVERAGE(Table1[Rating]) -> 3.966782
A5: OD5817020004 | B5: 46077 | C5: Yash Wardhan | D5: Kolkata | E5: West Bengal | F5: Electronics | G5: Smartphone | H5: Realme | I5: RetailNet | J5: 1 | K5: 5514 | L5: 0 | M5: =J5*K5*(1-L5) -> 5514 | N5: =M5*0.18 -> 992.52 | O5: Credit Card | P5: Delivered | Q5: 5 | R5: No Return
A6: OD7170960005 | B6: 45819 | C6: Divya Dutta | D6: Bangalore | E6: Karnataka | F6: Electronics | G6: Wireless Earbuds | H6: boAt | I6: IndiFlashMart | J6: 1 | K6: 56364 | L6: 0.2 | M6: =J6*K6*(1-L6) -> 45091.2 | N6: =M6*0.23 -> 10370.976 | O6: Net Banking | P6: Delivered | Q6: 5 | R6: No Return
A7: OD2893940006 | B7: 46049 | C7: Shilpa Shetty | D7: Mumbai | E7: Maharashtra | F7: Home & Kitchen | G7: Bedsheet Set | H7: Bombay Dyeing | I7: SaneRetails | J7: 1 | K7: 3192 | L7: 0.15 | M7: =J7*K7*(1-L7) -> 2713.2 | N7: =M7*0.21 -> 569.772 | O7: Net Banking | P7: Delivered | Q7: 5 | R7: No Return | U7: =COUNTA(Table1[Customer Name]) -> 1500
A8: OD9199100007 | B8: 45795 | C8: Vikram Singh | D8: Mumbai | E8: Maharashtra | F8: Electronics | G8: Smart TV | H8: Samsung | I8: IndiFlashMart | J8: 1 | K8: 43068 | L8: 0.15 | M8: =J8*K8*(1-L8) -> 36607.8 | N8: =M8*0.2 -> 7321.56 | O8: Cash on Delivery (COD) | P8: Delivered | Q8: 3 | R8: No Return | U8: =AVERAGE(Table1[Unit Price]) -> 9994.8873
A9: OD9233690008 | B9: 45811 | C9: Shilpa Shetty | D9: Guwahati | E9: Assam | F9: Home & Kitchen | G9: Bedsheet Set | H9: Bombay Dyeing | I9: OmniTechRetail | J9: 2 | K9: 359 | L9: 0.05 | M9: =J9*K9*(1-L9) -> 682.1 | N9: =M9*0.15 -> 102.315 | O9: Debit Card | P9: Delivered | Q9: 5 | R9: No Return | U9: =AVERAGE(Table1[Revenue]) -> 13610.033
A10: OD6105490009 | B10: 45678 | C10: Rohan Das | D10: Kochi | E10: Kerala | F10: Beauty & Grooming | G10: Sunscreen | H10: Neutrogena | I10: TrueComRetail | J10: 4 | K10: 201 | L10: 0 | M10: =J10*K10*(1-L10) -> 804 | N10: =-0.08*M10 -> -64.32 | O10: Net Banking | P10: Returned | Q10: 1 | R10: Returned
A11: OD4288370010 | B11: 45714 | C11: Aditi Rao | D11: Lucknow | E11: Uttar Pradesh | F11: Home & Kitchen | G11: Bedsheet Set | H11: Bombay Dyeing | I11: OmniTechRetail | J11: 1 | K11: 819 | L11: 0.2 | M11: =J11*K11*(1-L11) -> 655.2 | N11: =M11*0.14 -> 91.728 | O11: Net Banking | P11: Delivered | Q11: 4 | R11: No Return
A12: OD2389910011 | B12: 45917 | C12: Deepak Kumar | D12: Chandigarh | E12: Punjab | F12: Home & Kitchen | G12: Air Fryer | H12: Kent | I12: OmniTechRetail | J12: 1 | K12: 4017 | L12: 0.15 | M12: =J12*K12*(1-L12) -> 3414.45 | N12: =M12*0.13 -> 443.8785 | O12: UPI | P12: Delivered | Q12: 3 | R12: No Return
A13: OD7594310012 | B13: 46002 | C13: Ananya Iyer | D13: Guwahati | E13: Assam | F13: Clothing & Fashion | G13: Sports Shoes | H13: Puma | I13: SuperComNet | J13: 1 | K13: 1906 | L13: 0 | M13: =J13*K13*(1-L13) -> 1906 | N13: =M13*0.22 -> 419.32 | O13: Net Banking | P13: Delivered | Q13: 5 | R13: No Return
A14: OD1468310013 | B14: 46037 | C14: Kriti Malhotra | D14: Mumbai | E14: Maharashtra | F14: Electronics | G14: Wireless Earbuds | H14: boAt | I14: RetailNet | J14: 1 | K14: 32563 | L14: 0.2 | M14: =J14*K14*(1-L14) -> 26050.4 | N14: =M14*0.2 -> 5210.08 | O14: UPI | P14: Delivered | Q14: 3 | R14: No Return
A15: OD7647860014 | B15: 45707 | C15: Deepak Kumar | D15: Delhi | E15: Delhi | F15: Home & Kitchen | G15: Air Fryer | H15: Kent | I15: SaneRetails | J15: 1 | K15: 5878 | L15: 0.1 | M15: =J15*K15*(1-L15) -> 5290.2 | N15: =M15*0.25 -> 1322.55 | O15: Net Banking | P15: Delivered | Q15: 4 | R15: No Return
A16: OD2519700015 | B16: 45907 | C16: Vikram Singh | D16: Hyderabad | E16: Telangana | F16: Clothing & Fashion | G16: Casual T-Shirt | H16: Roadster | I16: SuperComNet | J16: 2 | K16: 3941 | L16: 0.1 | M16: =J16*K16*(1-L16) -> 7093.8 | N16: =M16*0.14 -> 993.132 | O16: Net Banking | P16: Delivered | Q16: 5 | R16: No Return
A17: OD5762740016 | B17: 46081 | C17: Aarav Sharma | D17: Patna | E17: Bihar | F17: Clothing & Fashion | G17: Casual T-Shirt | H17: Roadster | I17: TrueComRetail | J17: 1 | K17: 4389 | L17: 0.05 | M17: =J17*K17*(1-L17) -> 4169.55 | N17: =M17*0.19 -> 792.2145 | O17: Credit Card | P17: Delivered | Q17: 4 | R17: No Return
A18: OD5863060017 | B18: 45922 | C18: Aditi Rao | D18: Delhi | E18: Delhi | F18: Beauty & Grooming | G18: Sunscreen | H18: Neutrogena | I18: RetailNet | J18: 2 | K18: 192 | L18: 0.15 | M18: =J18*K18*(1-L18) -> 326.4 | N18: =M18*0.21 -> 68.544 | O18: UPI | P18: Delivered | Q18: 4 | R18: No Return
A19: OD2394080018 | B19: 45694 | C19: Vikram Singh | D19: Kochi | E19: Kerala | F19: Home & Kitchen | G19: Air Fryer | H19: Kent | I19: OmniTechRetail | J19: 4 | K19: 1168 | L19: 0.05 | M19: =J19*K19*(1-L19) -> 4438.4 | N19: =M19*0.1 -> 443.84 | O19: Net Banking | P19: Delivered | Q19: 5 | R19: No Return
A20: OD6689710019 | B20: 46029 | C20: Neha Gupta | D20: Ahmedabad | E20: Gujarat | F20: Beauty & Grooming | G20: Beard Trimmer | H20: L'Oreal | I20: TrueComRetail | J20: 1 | K20: 2374 | L20: 0.05 | M20: =J20*K20*(1-L20) -> 2255.3 | N20: =M20*0.1 -> 225.53 | O20: Cash on Delivery (COD) | P20: Delivered | Q20: 3 | R20: No Return
A21: OD5164440020 | B21: 45773 | C21: Vivek Agnihotri | D21: Bhopal | E21: Madhya Pradesh | F21: Home & Kitchen | G21: Non-Stick Pan | H21: Hawkins | I21: OmniTechRetail | J21: 2 | K21: 2406 | L21: 0 | M21: =J21*K21*(1-L21) -> 4812 | N21: =M21*0.25 -> 1203 | O21: Debit Card | P21: Delivered | Q21: 3 | R21: No Return
A22: OD7944860021 | B22: 46096 | C22: Neha Gupta | D22: Lucknow | E22: Uttar Pradesh | F22: Beauty & Grooming | G22: Face Wash | H22: Nivea | I22: RetailNet | J22: 1 | K22: 2163 | L22: 0 | M22: =J22*K22*(1-L22) -> 2163 | N22: =M22*0.15 -> 324.45 | O22: UPI | P22: Delivered | Q22: 5 | R22: No Return
A23: OD7028500022 | B23: 46083 | C23: Karan Johar | D23: Chandigarh | E23: Punjab | F23: Electronics | G23: Power Bank | H23: Mi | I23: IndiFlashMart | J23: 2 | K23: 61585 | L23: 0 | M23: =J23*K23*(1-L23) -> 123170 | N23: =M23*0.15 -> 18475.5 | O23: Net Banking | P23: Delivered | Q23: 4 | R23: No Return
A24: OD4198650023 | B24: 45960 | C24: Amit Verma | D24: Chandigarh | E24: Punjab | F24: Beauty & Grooming | G24: Hair Dryer | H24: Philips | I24: TrueComRetail | J24: 1 | K24: 1887 | L24: 0.15 | M24: 0 | N24: 0 | O24: Debit Card | P24: Cancelled | R24: Not Applicable
A25: OD6063100024 | B25: 46061 | C25: Aarav Sharma | D25: Chennai | E25: Tamil Nadu | F25: Beauty & Grooming | G25: Perfume | H25: Beardo | I25: TrueComRetail | J25: 1 | K25: 2261 | L25: 0.15 | M25: =J25*K25*(1-L25) -> 1921.85 | N25: =M25*0.25 -> 480.4625 | O25: Credit Card | P25: Delivered | Q25: 5 | R25: No Return
A26: OD3902980025 | B26: 45752 | C26: Sunil Gavaskar | D26: Mumbai | E26: Maharashtra | F26: Electronics | G26: Smartwatch | H26: Noise | I26: IndiFlashMart | J26: 1 | K26: 63361 | L26: 0.05 | M26: =J26*K26*(1-L26) -> 60192.95 | N26: =M26*0.13 -> 7825.0835 | O26: UPI | P26: Delivered | Q26: 4 | R26: No Return
A27: OD3811000026 | B27: 45720 | C27: Divya Dutta | D27: Ahmedabad | E27: Gujarat | F27: Beauty & Grooming | G27: Beard Trimmer | H27: L'Oreal | I27: TrueComRetail | J27: 1 | K27: 2103 | L27: 0.15 | M27: =J27*K27*(1-L27) -> 1787.55 | N27: =M27*0.22 -> 393.261 | O27: Cash on Delivery (COD) | P27: Delivered | Q27: 5 | R27: No Return
A28: OD6618100027 | B28: 45664 | C28: Priya Patel | D28: Lucknow | E28: Uttar Pradesh | F28: Home & Kitchen | G28: Air Fryer | H28: Kent | I28: SaneRetails | J28: 1 | K28: 2433 | L28: 0 | M28: =J28*K28*(1-L28) -> 2433 | N28: =M28*0.17 -> 413.61 | O28: Cash on Delivery (COD) | P28: Delivered | Q28: 5 | R28: No Return
A29: OD9237890028 | B29: 45801 | C29: Sunil Gavaskar | D29: Bhopal | E29: Madhya Pradesh | F29: Home & Kitchen | G29: Non-Stick Pan | H29: Hawkins | I29: OmniTechRetail | J29: 1 | K29: 5318 | L29: 0.05 | M29: =J29*K29*(1-L29) -> 5052.1 | N29: =M29*0.24 -> 1212.504 | O29: Cash on Delivery (COD) | P29: Delivered | Q29: 4 | R29: No Return
A30: OD6626240029 | B30: 45712 | C30: Meera Bai | D30: Chandigarh | E30: Punjab | F30: Electronics | G30: Wireless Earbuds | H30: boAt | I30: RetailNet | J30: 1 | K30: 27907 | L30: 0.2 | M30: =J30*K30*(1-L30) -> 22325.6 | N30: =-0.08*M30 -> -1786.048 | O30: Credit Card | P30: Returned | Q30: 1 | R30: Returned
A31: OD6855220030 | B31: 46060 | C31: Alok Nath | D31: Delhi | E31: Delhi | F31: Electronics | G31: Smartphone | H31: Realme | I31: RetailNet | J31: 1 | K31: 24250 | L31: 0 | M31: =J31*K31*(1-L31) -> 24250 | N31: =M31*0.1 -> 2425 | O31: Cash on Delivery (COD) | P31: Delivered | Q31: 3 | R31: No Return
A32: OD2812950031 | B32: 46089 | C32: Amit Verma | D32: Jaipur | E32: Rajasthan | F32: Beauty & Grooming | G32: Face Wash | H32: Nivea | I32: TrueComRetail | J32: 1 | K32: 2190 | L32: 0.1 | M32: =J32*K32*(1-L32) -> 1971 | N32: =M32*0.15 -> 295.65 | O32: Cash on Delivery (COD) | P32: Delivered | Q32: 5 | R32: No Return
A33: OD8837560032 | B33: 45753 | C33: Karan Johar | D33: Mumbai | E33: Maharashtra | F33: Beauty & Grooming | G33: Sunscreen | H33: Neutrogena | I33: RetailNet | J33: 1 | K33: 791 | L33: 0.05 | M33: =J33*K33*(1-L33) -> 751.45 | N33: =M33*0.19 -> 142.7755 | O33: Net Banking | P33: Delivered | Q33: 4 | R33: No Return
A34: OD3323770033 | B34: 45986 | C34: Divya Dutta | D34: Pune | E34: Maharashtra | F34: Beauty & Grooming | G34: Hair Dryer | H34: Philips | I34: RetailNet | J34: 1 | K34: 532 | L34: 0.15 | M34: =J34*K34*(1-L34) -> 452.2 | N34: =M34*0.26 -> 117.572 | O34: Credit Card | P34: Delivered | Q34: 5 | R34: No Return
A35: OD2702390034 | B35: 45852 | C35: Riya Sen | D35: Delhi | E35: Delhi | F35: Electronics | G35: Smartwatch | H35: Noise | I35: RetailNet | J35: 1 | K35: 62874 | L35: 0 | M35: =J35*K35*(1-L35) -> 62874 | N35: =M35*0.22 -> 13832.28 | O35: UPI | P35: Delivered | Q35: 4 | R35: No Return
A36: OD1865510035 | B36: 45936 | C36: Aarav Sharma | D36: Jaipur | E36: Rajasthan | F36: Beauty & Grooming | G36: Beard Trimmer | H36: L'Oreal | I36: TrueComRetail | J36: 2 | K36: 408 | L36: 0.05 | M36: =J36*K36*(1-L36) -> 775.2 | N36: =M36*0.25 -> 193.8 | O36: Net Banking | P36: Delivered | Q36: 4 | R36: No Return
A37: OD3430780036 | B37: 46075 | C37: Pooja Nair | D37: Jaipur | E37: Rajasthan | F37: Electronics | G37: Wireless Earbuds | H37: boAt | I37: RetailNet | J37: 2 | K37: 24079 | L37: 0.05 | M37: =J37*K37*(1-L37) -> 45750.1 | N37: =M37*0.24 -> 10980.024 | O37: Net Banking | P37: Delivered | Q37: 5 | R37: No Return
A38: OD1159150037 | B38: 46094 | C38: Priya Patel | D38: Lucknow | E38: Uttar Pradesh | F38: Clothing & Fashion | G38: Leather Jacket | H38: Zara | I38: TrueComRetail | J38: 1 | K38: 1891 | L38: 0.15 | M38: =J38*K38*(1-L38) -> 1607.35 | N38: =M38*0.21 -> 337.5435 | O38: Credit Card | P38: Delivered | Q38: 4 | R38: No Return
A39: OD7371940038 | B39: 45668 | C39: Rohan Das | D39: Mumbai | E39: Maharashtra | F39: Electronics | G39: Smart TV | H39: Samsung | I39: IndiFlashMart | J39: 1 | K39: 60770 | L39: 0.2 | M39: =J39*K39*(1-L39) -> 48616 | N39: =M39*0.17 -> 8264.72 | O39: Cash on Delivery (COD) | P39: Delivered | Q39: 4 | R39: No Return
A40: OD8111680039 | B40: 45865 | C40: Jyoti Mishra | D40: Lucknow | E40: Uttar Pradesh | F40: Beauty & Grooming | G40: Sunscreen | H40: Neutrogena | I40: TrueComRetail | J40: 1 | K40: 888 | L40: 0.1 | M40: =J40*K40*(1-L40) -> 799.2 | N40: =M40*0.17 -> 135.864 | O40: Net Banking | P40: Delivered | Q40: 5 | R40: No Return
A41: OD4142790040 | B41: 45695 | C41: Rahul Joshi | D41: Kolkata | E41: West Bengal | F41: Home & Kitchen | G41: Mixer Grinder | H41: Prestige | I41: OmniTechRetail | J41: 1 | K41: 5197 | L41: 0.1 | M41: =J41*K41*(1-L41) -> 4677.3 | N41: =M41*0.22 -> 1029.006 | O41: Credit Card | P41: Delivered | Q41: 5 | R41: No Return
A42: OD2949990041 | B42: 45890 | C42: Riya Sen | D42: Kochi | E42: Kerala | F42: Electronics | G42: Power Bank | H42: Mi | I42: RetailNet | J42: 1 | K42: 40625 | L42: 0.15 | M42: 0 | N42: 0 | O42: Credit Card | P42: Cancelled | R42: Not Applicable
A43: OD6014580042 | B43: 46079 | C43: Jyoti Mishra | D43: Lucknow | E43: Uttar Pradesh | F43: Beauty & Grooming | G43: Beard Trimmer | H43: L'Oreal | I43: TrueComRetail | J43: 2 | K43: 1081 | L43: 0.1 | M43: =J43*K43*(1-L43) -> 1945.8 | N43: =M43*0.13 -> 252.954 | O43: Cash on Delivery (COD) | P43: Delivered | Q43: 4 | R43: No Return
A44: OD2732200043 | B44: 45987 | C44: Meera Bai | D44: Hyderabad | E44: Telangana | F44: Clothing & Fashion | G44: Socks Pack | H44: Peter England | I44: SuperComNet | J44: 4 | K44: 2917 | L44: 0 | M44: =J44*K44*(1-L44) -> 11668 | N44: =M44*0.12 -> 1400.16 | O44: UPI | P44: Delivered | Q44: 4 | R44: No Return
A45: OD4645960044 | B45: 45743 | C45: Aditi Rao | D45: Delhi | E45: Delhi | F45: Clothing & Fashion | G45: Ethnic Kurta | H45: Wrogn | I45: TrueComRetail | J45: 1 | K45: 4486 | L45: 0.05 | M45: =J45*K45*(1-L45) -> 4261.7 | N45: =M45*0.13 -> 554.021 | O45: UPI | P45: Delivered | Q45: 3 | R45: No Return
A46: OD7967230045 | B46: 45702 | C46: Sunil Gavaskar | D46: Ahmedabad | E46: Gujarat | F46: Electronics | G46: Smart TV | H46: Samsung | I46: RetailNet | J46: 3 | K46: 18608 | L46: 0.1 | M46: =J46*K46*(1-L46) -> 50241.6 | N46: =M46*0.22 -> 11053.152 | O46: Credit Card | P46: Delivered | Q46: 5 | R46: No Return
A47: OD1625380046 | B47: 45995 | C47: Sanjay Rao | D47: Bhopal | E47: Madhya Pradesh | F47: Electronics | G47: Smartwatch | H47: Noise | I47: RetailNet | J47: 1 | K47: 44939 | L47: 0.05 | M47: =J47*K47*(1-L47) -> 42692.05 | N47: =M47*0.21 -> 8965.3305 | O47: Cash on Delivery (COD) | P47: Delivered | Q47: 3 | R47: No Return
A48: OD1588080047 | B48: 45755 | C48: Ananya Iyer | D48: Pune | E48: Maharashtra | F48: Beauty & Grooming | G48: Face Wash | H48: Nivea | I48: TrueComRetail | J48: 2 | K48: 1528 | L48: 0 | M48: =J48*K48*(1-L48) -> 3056 | N48: =M48*0.2 -> 611.2 | O48: UPI | P48: Delivered | Q48: 5 | R48: No Return
A49: OD4249890048 | B49: 45953 | C49: Sneha Reddy | D49: Ahmedabad | E49: Gujarat | F49: Home & Kitchen | G49: Water Bottle | H49: Milton | I49: SaneRetails | J49: 2 | K49: 2625 | L49: 0.1 | M49: =J49*K49*(1-L49) -> 4725 | N49: =-0.08*M49 -> -378 | O49: Net Banking | P49: Returned | Q49: 1 | R49: Returned
A50: OD7058170049 | B50: 45919 | C50: Ananya Iyer | D50: Bangalore | E50: Karnataka | F50: Clothing & Fashion | G50: Sports Shoes | H50: Puma | I50: SuperComNet | J50: 1 | K50: 3130 | L50: 0.1 | M50: =J50*K50*(1-L50) -> 2817 | N50: =M50*0.23 -> 647.91 | O50: Debit Card | P50: Delivered | Q50: 5 | R50: No Return
A51: OD5530850050 | B51: 45893 | C51: Aarav Sharma | D51: Lucknow | E51: Uttar Pradesh | F51: Home & Kitchen | G51: Bedsheet Set | H51: Bombay Dyeing | I51: OmniTechRetail | J51: 2 | K51: 1215 | L51: 0.1 | M51: =J51*K51*(1-L51) -> 2187 | N51: =M51*0.15 -> 328.05 | O51: Debit Card | P51: Delivered | Q51: 5 | R51: No Return
A52: OD5238750051 | B52: 46038 | C52: Divya Dutta | D52: Ahmedabad | E52: Gujarat | F52: Clothing & Fashion | G52: Sports Shoes | H52: Puma | I52: SuperComNet | J52: 1 | K52: 304 | L52: 0.05 | M52: =J52*K52*(1-L52) -> 288.8 | N52: =M52*0.26 -> 75.088 | O52: Net Banking | P52: Delivered | Q52: 5 | R52: No Return
A53: OD9270570052 | B53: 45889 | C53: Amit Verma | D53: Delhi | E53: Delhi | F53: Electronics | G53: Power Bank | H53: Mi | I53: RetailNet | J53: 1 | K53: 54577 | L53: 0.2 | M53: =J53*K53*(1-L53) -> 43661.6 | N53: =M53*0.24 -> 10478.784 | O53: Net Banking | P53: Delivered | Q53: 3 | R53: No Return
A54: OD8029060053 | B54: 45877 | C54: Karan Johar | D54: Guwahati | E54: Assam | F54: Beauty & Grooming | G54: Sunscreen | H54: Neutrogena | I54: RetailNet | J54: 1 | K54: 1550 | L54: 0.2 | M54: =J54*K54*(1-L54) -> 1240 | N54: =-0.08*M54 -> -99.2 | O54: UPI | P54: Returned | Q54: 1 | R54: Returned
A55: OD7651450054 | B55: 45662 | C55: Sanjay Rao | D55: Mumbai | E55: Maharashtra | F55: Clothing & Fashion | G55: Leather Jacket | H55: Zara | I55: SuperComNet | J55: 3 | K55: 3220 | L55: 0 | M55: =J55*K55*(1-L55) -> 9660 | N55: =M55*0.24 -> 2318.4 | O55: Debit Card | P55: Delivered | Q55: 4 | R55: No Return
A56: OD4922490055 | B56: 45862 | C56: Shilpa Shetty | D56: Jaipur | E56: Rajasthan | F56: Home & Kitchen | G56: Mixer Grinder | H56: Prestige | I56: OmniTechRetail | J56: 1 | K56: 3939 | L56: 0.2 | M56: =J56*K56*(1-L56) -> 3151.2 | N56: =M56*0.12 -> 378.144 | O56: Cash on Delivery (COD) | P56: Delivered | Q56: 4 | R56: No Return
A57: OD4982880056 | B57: 45687 | C57: Neha Gupta | D57: Delhi | E57: Delhi | F57: Clothing & Fashion | G57: Socks Pack | H57: Peter England | I57: TrueComRetail | J57: 1 | K57: 1734 | L57: 0 | M57: =J57*K57*(1-L57) -> 1734 | N57: =M57*0.18 -> 312.12 | O57: Credit Card | P57: Delivered | Q57: 4 | R57: No Return
A58: OD4395720057 | B58: 45961 | C58: Sanjay Rao | D58: Mumbai | E58: Maharashtra | F58: Home & Kitchen | G58: Non-Stick Pan | H58: Hawkins | I58: OmniTechRetail | J58: 2 | K58: 2913 | L58: 0.05 | M58: =J58*K58*(1-L58) -> 5534.7 | N58: =M58*0.13 -> 719.511 | O58: Net Banking | P58: Delivered | Q58: 3 | R58: No Return
A59: OD5257520058 | B59: 45948 | C59: Ananya Iyer | D59: Bhopal | E59: Madhya Pradesh | F59: Beauty & Grooming | G59: Sunscreen | H59: Neutrogena | I59: RetailNet | J59: 1 | K59: 2137 | L59: 0 | M59: =J59*K59*(1-L59) -> 2137 | N59: =M59*0.11 -> 235.07 | O59: UPI | P59: Delivered | Q59: 5 | R59: No Return
A60: OD1494750059 | B60: 45826 | C60: Jyoti Mishra | D60: Bangalore | E60: Karnataka | F60: Electronics | G60: Power Bank | H60: Mi | I60: IndiFlashMart | J60: 1 | K60: 44994 | L60: 0.05 | M60: =J60*K60*(1-L60) -> 42744.3 | N60: =M60*0.2 -> 8548.86 | O60: Credit Card | P60: Delivered | Q60: 3 | R60: No Return
A61: OD6989060060 | B61: 46025 | C61: Sunil Gavaskar | D61: Lucknow | E61: Uttar Pradesh | F61: Electronics | G61: Smart TV | H61: Samsung | I61: RetailNet | J61: 1 | K61: 9368 | L61: 0 | M61: =J61*K61*(1-L61) -> 9368 | N61: =M61*0.11 -> 1030.48 | O61: Debit Card | P61: Delivered | Q61: 3 | R61: No Return
A62: OD2126320061 | B62: 45838 | C62: Deepak Kumar | D62: Hyderabad | E62: Telangana | F62: Clothing & Fashion | G62: Casual T-Shirt | H62: Roadster | I62: TrueComRetail | J62: 1 | K62: 3479 | L62: 0.15 | M62: =J62*K62*(1-L62) -> 2957.15 | N62: =M62*0.16 -> 473.144 | O62: Credit Card | P62: Delivered | Q62: 5 | R62: No Return
A63: OD9794430062 | B63: 45724 | C63: Rahul Joshi | D63: Jaipur | E63: Rajasthan | F63: Clothing & Fashion | G63: Socks Pack | H63: Peter England | I63: SuperComNet | J63: 4 | K63: 2872 | L63: 0.15 | M63: =J63*K63*(1-L63) -> 9764.8 | N63: =M63*0.15 -> 1464.72 | O63: UPI | P63: Delivered | Q63: 5 | R63: No Return
A64: OD3818050063 | B64: 45757 | C64: Vikram Singh | D64: Hyderabad | E64: Telangana | F64: Beauty & Grooming | G64: Face Wash | H64: Nivea | I64: RetailNet | J64: 1 | K64: 2375 | L64: 0.2 | M64: =J64*K64*(1-L64) -> 1900 | N64: =M64*0.12 -> 228 | O64: Net Banking | P64: Delivered | Q64: 5 | R64: No Return
A65: OD7211880064 | B65: 45821 | C65: Pooja Nair | D65: Lucknow | E65: Uttar Pradesh | F65: Clothing & Fashion | G65: Socks Pack | H65: Peter England | I65: SuperComNet | J65: 4 | K65: 4220 | L65: 0.05 | M65: =J65*K65*(1-L65) -> 16036 | N65: =M65*0.19 -> 3046.84 | O65: Net Banking | P65: Delivered | Q65: 3 | R65: No Return
A66: OD1836620065 | B66: 45705 | C66: Pooja Nair | D66: Bhopal | E66: Madhya Pradesh | F66: Electronics | G66: Power Bank | H66: Mi | I66: IndiFlashMart | J66: 1 | K66: 40086 | L66: 0.15 | M66: =J66*K66*(1-L66) -> 34073.1 | N66: =M66*0.13 -> 4429.503 | O66: Credit Card | P66: Delivered | Q66: 3 | R66: No Return
A67: OD8866030066 | B67: 45994 | C67: Amit Verma | D67: Patna | E67: Bihar | F67: Clothing & Fashion | G67: Sports Shoes | H67: Puma | I67: TrueComRetail | J67: 1 | K67: 1261 | L67: 0.05 | M67: =J67*K67*(1-L67) -> 1197.95 | N67: =M67*0.2 -> 239.59 | O67: Credit Card | P67: Delivered | Q67: 4 | R67: No Return
A68: OD7144500067 | B68: 45742 | C68: Aarav Sharma | D68: Kolkata | E68: West Bengal | F68: Beauty & Grooming | G68: Perfume | H68: Beardo | I68: TrueComRetail | J68: 1 | K68: 519 | L68: 0 | M68: =J68*K68*(1-L68) -> 519 | N68: =M68*0.21 -> 108.99 | O68: UPI | P68: Delivered | Q68: 4 | R68: No Return
A69: OD3424540068 | B69: 45923 | C69: Shilpa Shetty | D69: Pune | E69: Maharashtra | F69: Electronics | G69: Smartwatch | H69: Noise | I69: IndiFlashMart | J69: 1 | K69: 11611 | L69: 0.15 | M69: =J69*K69*(1-L69) -> 9869.35 | N69: =M69*0.17 -> 1677.7895 | O69: UPI | P69: Delivered | Q69: 3 | R69: No Return
A70: OD5112500069 | B70: 45828 | C70: Aditi Rao | D70: Pune | E70: Maharashtra | F70: Clothing & Fashion | G70: Leather Jacket | H70: Zara | I70: SuperComNet | J70: 2 | K70: 569 | L70: 0.05 | M70: =J70*K70*(1-L70) -> 1081.1 | N70: =M70*0.24 -> 259.464 | O70: Cash on Delivery (COD) | P70: Delivered | Q70: 4 | R70: No Return
A71: OD7059030070 | B71: 45752 | C71: Divya Dutta | D71: Patna | E71: Bihar | F71: Beauty & Grooming | G71: Beard Trimmer | H71: L'Oreal | I71: RetailNet | J71: 1 | K71: 468 | L71: 0.15 | M71: =J71*K71*(1-L71) -> 397.8 | N71: =M71*0.21 -> 83.538 | O71: UPI | P71: Delivered | Q71: 3 | R71: No Return
A72: OD7799600071 | B72: 45695 | C72: Rohan Das | D72: Hyderabad | E72: Telangana | F72: Beauty & Grooming | G72: Perfume | H72: Beardo | I72: TrueComRetail | J72: 3 | K72: 656 | L72: 0.15 | M72: =J72*K72*(1-L72) -> 1672.8 | N72: =M72*0.17 -> 284.376 | O72: Net Banking | P72: Delivered | Q72: 3 | R72: No Return
A73: OD3808990072 | B73: 45670 | C73: Meera Bai | D73: Lucknow | E73: Uttar Pradesh | F73: Home & Kitchen | G73: Water Bottle | H73: Milton | I73: OmniTechRetail | J73: 2 | K73: 1022 | L73: 0 | M73: =J73*K73*(1-L73) -> 2044 | N73: =M73*0.25 -> 511 | O73: Net Banking | P73: Delivered | Q73: 4 | R73: No Return
A74: OD3620230073 | B74: 46009 | C74: Sanjay Rao | D74: Patna | E74: Bihar | F74: Beauty & Grooming | G74: Face Wash | H74: Nivea | I74: RetailNet | J74: 5 | K74: 1286 | L74: 0.2 | M74: =J74*K74*(1-L74) -> 5144 | N74: =M74*0.14 -> 720.16 | O74: Net Banking | P74: Delivered | Q74: 5 | R74: No Return
A75: OD6977580074 | B75: 45696 | C75: Sanjay Rao | D75: Patna | E75: Bihar | F75: Electronics | G75: Smart TV | H75: Samsung | I75: IndiFlashMart | J75: 2 | K75: 30446 | L75: 0 | M75: =J75*K75*(1-L75) -> 60892 | N75: =M75*0.2 -> 12178.4 | O75: Credit Card | P75: Delivered | Q75: 3 | R75: No Return
A76: OD8697270075 | B76: 45966 | C76: Yash Wardhan | D76: Kochi | E76: Kerala | F76: Home & Kitchen | G76: Bedsheet Set | H76: Bombay Dyeing | I76: SaneRetails | J76: 3 | K76: 4394 | L76: 0.05 | M76: =J76*K76*(1-L76) -> 12522.9 | N76: =M76*0.16 -> 2003.664 | O76: Cash on Delivery (COD) | P76: Delivered | Q76: 5 | R76: No Return
A77: OD1792830076 | B77: 45774 | C77: Pooja Nair | D77: Patna | E77: Bihar | F77: Beauty & Grooming | G77: Hair Dryer | H77: Philips | I77: TrueComRetail | J77: 1 | K77: 2110 | L77: 0 | M77: =J77*K77*(1-L77) -> 2110 | N77: =M77*0.21 -> 443.1 | O77: Debit Card | P77: Delivered | Q77: 4 | R77: No Return
A78: OD1189280077 | B78: 45944 | C78: Riya Sen | D78: Lucknow | E78: Uttar Pradesh | F78: Clothing & Fashion | G78: Ethnic Kurta | H78: Wrogn | I78: SuperComNet | J78: 2 | K78: 1359 | L78: 0.2 | M78: =J78*K78*(1-L78) -> 2174.4 | N78: =M78*0.1 -> 217.44 | O78: Credit Card | P78: Delivered | Q78: 4 | R78: No Return
A79: OD8320990078 | B79: 46007 | C79: Vivek Agnihotri | D79: Chandigarh | E79: Punjab | F79: Clothing & Fashion | G79: Casual T-Shirt | H79: Roadster | I79: TrueComRetail | J79: 1 | K79: 587 | L79: 0.05 | M79: =J79*K79*(1-L79) -> 557.65 | N79: =M79*0.1 -> 55.765 | O79: Credit Card | P79: Delivered | Q79: 5 | R79: No Return
A80: OD4320150079 | B80: 45686 | C80: Sanjay Rao | D80: Kochi | E80: Kerala | F80: Clothing & Fashion | G80: Slim Fit Jeans | H80: Levis | I80: SuperComNet | J80: 2 | K80: 2261 | L80: 0.35 | M80: =J80*K80*(1-L80) -> 2939.3 | N80: =M80*0.15 -> 440.895 | O80: Debit Card | P80: Delivered | Q80: 3 | R80: No Return
A81: OD8161860080 | B81: 46016 | C81: Amit Verma | D81: Patna | E81: Bihar | F81: Home & Kitchen | G81: Air Fryer | H81: Kent | I81: SaneRetails | J81: 4 | K81: 3249 | L81: 0.05 | M81: =J81*K81*(1-L81) -> 12346.2 | N81: =M81*0.18 -> 2222.316 | O81: Net Banking | P81: Delivered | Q81: 4 | R81: No Return
A82: OD3342810081 | B82: 45951 | C82: Meera Bai | D82: Bangalore | E82: Karnataka | F82: Clothing & Fashion | G82: Casual T-Shirt | H82: Roadster | I82: SuperComNet | J82: 1 | K82: 1369 | L82: 0.05 | M82: =J82*K82*(1-L82) -> 1300.55 | N82: =M82*0.2 -> 260.11 | O82: Net Banking | P82: Delivered | Q82: 5 | R82: No Return
A83: OD5175080082 | B83: 45886 | C83: Neha Gupta | D83: Bhopal | E83: Madhya Pradesh | F83: Clothing & Fashion | G83: Leather Jacket | H83: Zara | I83: TrueComRetail | J83: 1 | K83: 2670 | L83: 0.15 | M83: =J83*K83*(1-L83) -> 2269.5 | N83: =M83*0.25 -> 567.375 | O83: Debit Card | P83: Delivered | Q83: 4 | R83: No Return
A84: OD6918370083 | B84: 45958 | C84: Deepak Kumar | D84: Ahmedabad | E84: Gujarat | F84: Home & Kitchen | G84: Bedsheet Set | H84: Bombay Dyeing | I84: SaneRetails | J84: 2 | K84: 2074 | L84: 0.35 | M84: =J84*K84*(1-L84) -> 2696.2 | N84: =M84*0.14 -> 377.468 | O84: UPI | P84: Delivered | Q84: 3 | R84: No Return
A85: OD3115930084 | B85: 45716 | C85: Divya Dutta | D85: Bangalore | E85: Karnataka | F85: Home & Kitchen | G85: LED Bulb | H85: Philips | I85: SaneRetails | J85: 1 | K85: 1743 | L85: 0 | M85: =J85*K85*(1-L85) -> 1743 | N85: =M85*0.22 -> 383.46 | O85: Credit Card | P85: Delivered | Q85: 4 | R85: No Return
A86: OD9793350085 | B86: 45762 | C86: Arjun Choudhury | D86: Chennai | E86: Tamil Nadu | F86: Electronics | G86: Smart TV | H86: Samsung | I86: RetailNet | J86: 2 | K86: 42591 | L86: 0 | M86: =J86*K86*(1-L86) -> 85182 | N86: =M86*0.1 -> 8518.2 | O86: UPI | P86: Delivered | Q86: 5 | R86: No Return
A87: OD6551780086 | B87: 45726 | C87: Ananya Iyer | D87: Jaipur | E87: Rajasthan | F87: Clothing & Fashion | G87: Socks Pack | H87: Peter England | I87: SuperComNet | J87: 2 | K87: 339 | L87: 0.05 | M87: =J87*K87*(1-L87) -> 644.1 | N87: =M87*0.21 -> 135.261 | O87: Net Banking | P87: Delivered | Q87: 5 | R87: No Return
A88: OD6348080087 | B88: 45899 | C88: Sneha Reddy | D88: Bhopal | E88: Madhya Pradesh | F88: Electronics | G88: Power Bank | H88: Mi | I88: IndiFlashMart | J88: 3 | K88: 50706 | L88: 0.05 | M88: =J88*K88*(1-L88) -> 144512.1 | N88: =M88*0.14 -> 20231.694 | O88: Debit Card | P88: Delivered | Q88: 3 | R88: No Return
A89: OD5279870088 | B89: 46103 | C89: Riya Sen | D89: Hyderabad | E89: Telangana | F89: Beauty & Grooming | G89: Sunscreen | H89: Neutrogena | I89: TrueComRetail | J89: 5 | K89: 195 | L89: 0 | M89: =J89*K89*(1-L89) -> 975 | N89: =M89*0.2 -> 195 | O89: Cash on Delivery (COD) | P89: Delivered | Q89: 5 | R89: No Return
A90: OD4666690089 | B90: 45684 | C90: Pooja Nair | D90: Guwahati | E90: Assam | F90: Beauty & Grooming | G90: Hair Dryer | H90: Philips | I90: RetailNet | J90: 2 | K90: 330 | L90: 0 | M90: =J90*K90*(1-L90) -> 660 | N90: =M90*0.13 -> 85.8 | O90: Cash on Delivery (COD) | P90: Delivered | Q90: 3 | R90: No Return
A91: OD8905620090 | B91: 45750 | C91: Yash Wardhan | D91: Hyderabad | E91: Telangana | F91: Electronics | G91: Smart TV | H91: Samsung | I91: RetailNet | J91: 2 | K91: 36827 | L91: 0.05 | M91: =J91*K91*(1-L91) -> 69971.3 | N91: =M91*0.17 -> 11895.121 | O91: Net Banking | P91: Delivered | Q91: 4 | R91: No Return
A92: OD3833790091 | B92: 45955 | C92: Aarav Sharma | D92: Mumbai | E92: Maharashtra | F92: Electronics | G92: Power Bank | H92: Mi | I92: RetailNet | J92: 1 | K92: 36235 | L92: 0.35 | M92: 0 | N92: 0 | O92: Cash on Delivery (COD) | P92: Cancelled | R92: Not Applicable
A93: OD9288990092 | B93: 45887 | C93: Rahul Joshi | D93: Jaipur | E93: Rajasthan | F93: Home & Kitchen | G93: LED Bulb | H93: Philips | I93: OmniTechRetail | J93: 1 | K93: 4545 | L93: 0.15 | M93: =J93*K93*(1-L93) -> 3863.25 | N93: =M93*0.17 -> 656.7525 | O93: Cash on Delivery (COD) | P93: Delivered | Q93: 5 | R93: No Return
A94: OD9979890093 | B94: 45889 | C94: Sanjay Rao | D94: Bangalore | E94: Karnataka | F94: Home & Kitchen | G94: LED Bulb | H94: Philips | I94: SaneRetails | J94: 2 | K94: 3922 | L94: 0 | M94: =J94*K94*(1-L94) -> 7844 | N94: =M94*0.18 -> 1411.92 | O94: Credit Card | P94: Delivered | Q94: 5 | R94: No Return
A95: OD8195520094 | B95: 45697 | C95: Arjun Choudhury | D95: Chennai | E95: Tamil Nadu | F95: Beauty & Grooming | G95: Sunscreen | H95: Neutrogena | I95: TrueComRetail | J95: 1 | K95: 1806 | L95: 0.15 | M95: =J95*K95*(1-L95) -> 1535.1 | N95: =M95*0.13 -> 199.563 | O95: UPI | P95: Delivered | Q95: 5 | R95: No Return
A96: OD8417740095 | B96: 45955 | C96: Priya Patel | D96: Pune | E96: Maharashtra | F96: Clothing & Fashion | G96: Leather Jacket | H96: Zara | I96: TrueComRetail | J96: 2 | K96: 1515 | L96: 0.05 | M96: =J96*K96*(1-L96) -> 2878.5 | N96: =M96*0.11 -> 316.635 | O96: Debit Card | P96: Delivered | Q96: 4 | R96: No Return
A97: OD4366200096 | B97: 45991 | C97: Sneha Reddy | D97: Pune | E97: Maharashtra | F97: Electronics | G97: Wireless Earbuds | H97: boAt | I97: IndiFlashMart | J97: 5 | K97: 38292 | L97: 0.2 | M97: =J97*K97*(1-L97) -> 153168 | N97: =M97*0.13 -> 19911.84 | O97: Debit Card | P97: Delivered | Q97: 3 | R97: No Return
A98: OD7210180097 | B98: 46102 | C98: Yash Wardhan | D98: Mumbai | E98: Maharashtra | F98: Home & Kitchen | G98: Non-Stick Pan | H98: Hawkins | I98: SaneRetails | J98: 1 | K98: 1487 | L98: 0 | M98: =J98*K98*(1-L98) -> 1487 | N98: =M98*0.24 -> 356.88 | O98: UPI | P98: Delivered | Q98: 5 | R98: No Return
A99: OD7381210098 | B99: 45726 | C99: Neha Gupta | D99: Ahmedabad | E99: Gujarat | F99: Beauty & Grooming | G99: Face Wash | H99: Nivea | I99: TrueComRetail | J99: 1 | K99: 1953 | L99: 0.05 | M99: =J99*K99*(1-L99) -> 1855.35 | N99: =M99*0.21 -> 389.6235 | O99: Credit Card | P99: Delivered | Q99: 4 | R99: No Return
A100: OD2678190099 | B100: 46083 | C100: Rahul Joshi | D100: Bhopal | E100: Madhya Pradesh | F100: Beauty & Grooming | G100: Hair Dryer | H100: Philips | I100: TrueComRetail | J100: 1 | K100: 901 | L100: 0.15 | M100: =J100*K100*(1-L100) -> 765.85 | N100: =M100*0.14 -> 107.219 | O100: Credit Card | P100: Delivered | Q100: 3 | R100: No Return
...

Sheet Dashboard Summary
B2: FLIPKART PERFORMANCE DASHBOARD
B5: Total Orders | C5: Total Revenue | E5: Total Profit | F5: Average Rating | M5: Tumhare dataset me ye columns hain: | T5: 📦 Total Orders
B6: =COUNTA('Order Data'!A2:A1501) -> 1500 | C6: =SUM('Order Data'!M2:M1501) -> 20415050 | E6: =SUM('Order Data'!N2:N1501) -> 3586218.8 | F6: =AVERAGE('Order Data'!Q2:Q1501) -> 3.966782 | T6: 💰 Total Revenue
M7: Order ID | T7: 📈 Total Profit
M8: Order Date | T8: ⭐ Average Rating
B9: Category Performance Breakdown | M9: Customer Name | T9: 👥 Total Customers (Distinct Customer Name)
B10: Category | C10: Orders Count | D10: Total Revenue | E10: Total Profit | M10: City | T10: 🔄 Return Rate (%)
B11: Electronics | C11: =COUNTIF('Order Data'!F$2:F$1501, B11) -> 374 | D11: =SUMIF('Order Data'!F$2:F$1501, B11, 'Order Data'!M$2:M$1501) -> 16739190 | E11: =SUMIF('Order Data'!F$2:F$1501, B11, 'Order Data'!N$2:N$1501) -> 2951652.6 | M11: State | T11: 🚚 Delivery Success Rate
B12: Clothing & Fashion | C12: =COUNTIF('Order Data'!F$2:F$1501, B12) -> 376 | D12: =SUMIF('Order Data'!F$2:F$1501, B12, 'Order Data'!M$2:M$1501) -> 1282144.3 | E12: =SUMIF('Order Data'!F$2:F$1501, B12, 'Order Data'!N$2:N$1501) -> 220892.68 | M12: Category | T12: 💸 Average Order Value (AOV)
B13: Home & Kitchen | C13: =COUNTIF('Order Data'!F$2:F$1501, B13) -> 379 | D13: =SUMIF('Order Data'!F$2:F$1501, B13, 'Order Data'!M$2:M$1501) -> 1724233.3 | E13: =SUMIF('Order Data'!F$2:F$1501, B13, 'Order Data'!N$2:N$1501) -> 298014.25 | M13: Product
B14: Beauty & Grooming | C14: =COUNTIF('Order Data'!F$2:F$1501, B14) -> 371 | D14: =SUMIF('Order Data'!F$2:F$1501, B14, 'Order Data'!M$2:M$1501) -> 669482.85 | E14: =SUMIF('Order Data'!F$2:F$1501, B14, 'Order Data'!N$2:N$1501) -> 115659.3 | M14: Brand
B15: Total | C15: =SUM(C11:C14) -> 1500 | D15: =SUM(D11:D14) -> 20415050 | E15: =SUM(E11:E14) -> 3586218.8 | M15: Seller | T15: KPI | U15: Formula
M16: Quantity | T16: Total Orders | U16: COUNTA(Order ID)
M17: Unit Price | T17: Total Revenue | U17: SUM(Revenue)
M18: Discount | T18: Total Profit | U18: SUM(Profit)
D19: Product Analysis | F19: Payment Analysis | K19: Recommended Dashboard Layout | M19: Revenue | T19: Average Rating | U19: AVERAGE(Rating)
B20: 📦 Total Orders | M20: Profit | T20: Total Customers | U20: Remove Duplicates ya Pivot Table se Distinct Count
B21: 💰 Total Revenue | D21: Top 10 Products by Revenue | F21: Payment Mode Distribution | K21: Top Row (KPI Cards) | M21: Payment Mode | T21: Average Order Value | U21: Total Revenue / Total Orders
B22: 📈 Total Profit | D22: Top 10 Products by Profit | F22: UPI | M22: Delivery Status | T22: 📊 Top 10 Products by Revenue (Horizontal Bar)
B23: ⭐ Average Rating | D23: Category-wise Revenue | F23: Credit Card | K23: Total Orders | M23: Rating
B24: 👥 Total Customers (Distinct Customer Name) | D24: Category-wise Profit | F24: Debit Card | K24: Total Revenue | M24: Return Status
B25: 🔄 Return Rate (%) | D25: Brand-wise Sales | F25: Cash on Delivery | K25: Total Profit
B26: 🚚 Delivery Success Rate | D26: Brand-wise Profit | K26: Average Rating | T26: 🔹 Bottom Section
B27: 💸 Average Order Value (AOV) | F27: Pie Chart. | K27: Return Rate
K28: Average Order Value | T28: 🍩 Payment Mode Distribution (Donut Chart)
T29: 🍩 Delivery Status (Donut Chart)
D30: Customer Analysis | K30: Middle Row | T30: 🍩 Return Status (Donut Chart)
B31: Sales Analysis Charts | F31: Rating Analysis | T31: 📍 State-wise Revenue (Bar Chart)
D32: Top 10 Customers by Revenue | K32: Revenue Trend (Line Chart)
B33: Revenue by Month | D33: Top Customers by Orders | F33: Average Rating by Category | K33: Category-wise Revenue (Bar Chart)
B34: Profit by Month | D34: Average Rating by Customer (optional) | F34: Average Rating by Brand | K34: Brand-wise Revenue (Bar Chart)
B35: Orders by Month | F35: Rating Distribution (1–5) | T35: Slicers
B36: Revenue Trend Line | K36: Bottom Row
T37: Pivot Tables bana kar in par Slicers lagao:
D38: Location Analysis | K38: Revenue by State (Map/Bar)
F39: Discount Analysis | K39: Payment Mode (Donut Chart) | T39: Year
D40: Revenue by State | K40: Delivery Status (Donut Chart) | T40: Month
D41: Revenue by City | F41: Average Discount | K41: Return Status (Donut Chart) | T41: State
D42: Profit by State | F42: Discount vs Revenue | K42: Top 10 Products (Bar Chart) | T42: City
F43: Discount vs Profit | T43: Category
D44: Map use kar sakte ho agar Power BI me ho. | T44: Brand
T45: Seller
K46: Important DAX/Excel Measures | T46: Payment Mode
F47: Slicers (Filters) | T47: Delivery Status
D48: Delivery Analysis | K48: Total Revenue = SUM(Revenue) | T48: Return Status
F49: Dashboard me ye slicers zarur lagana: | K49: Total Profit = SUM(Profit)
D50: Delivery Status Breakdown (Delivered, Cancelled, Pending) | K50: Total Orders = COUNT(Order ID) | T50: Agar Excel 2016 ya uske baad ka version hai, to Slicers bahut achhe se kaam karenge.
D51: Delivery Status % | F51: Year | K51: Average Rating = AVERAGE(Rating)
F52: Month | K52: Total Customers = DISTINCTCOUNT(Customer Name)
D53: Pie Chart ya Donut Chart. | F53: State | K53: Average Order Value = Revenue / Total Orders
F54: City | K54: Return Rate = (Returned Orders / Total Orders) × 100 | T54: Dashboard Color Theme
F55: Category | K55: Delivery Success Rate = (Delivered Orders / Total Orders) × 100
F56: Brand | T56: Ek professional color combination use karo:
D57: Return Analysis | F57: Product
F58: Seller | T58: 🔵 Blue → Revenue
D59: Return vs No Return | F59: Payment Mode | T59: 🟢 Green → Profit
D60: Return % by Category | F60: Delivery Status | T60: 🟠 Orange → Orders
D61: Return % by Brand | F61: Return Status | T61: 🔴 Red → Returns
T62: ⚪ White Background
T63: ⚫ Light Grey Borders
T65: Isse dashboard clean aur corporate look dega.

Sheet Revenue Analysis
A2: Row Labels | B2: Sum of Profit | C2: Sum of Revenue
A3: Feb | B3: 529692.77 | C3: 2977172.1
A4: Jan | B4: 525504.79 | C4: 2908282.4
A5: Mar | B5: 454232.11 | C5: 2549825.3
A6: Aug | B6: 255159.91 | C6: 1528879.4
A7: Nov | B7: 248307.71 | C7: 1462648
A8: Apr | B8: 260702.61 | C8: 1388847.4
A9: Dec | B9: 220765.1 | C9: 1369319.3
A10: Jun | B10: 228597.03 | C10: 1348702.9
A11: Sep | B11: 245911.29 | C11: 1307186.8
A12: Jul | B12: 215594.06 | C12: 1224880.3
A13: Oct | B13: 203420.53 | C13: 1222922.9
A14: May | B14: 198330.89 | C14: 1126383.4
A15: Grand Total | B15: 3586218.8 | C15: 20415050
A21: Row Labels | B21: Sum of Profit
A22: Jan | B22: 525504.79
A23: Feb | B23: 529692.77
A24: Mar | B24: 454232.11
A25: Apr | B25: 260702.61
A26: May | B26: 198330.89
A27: Jun | B27: 228597.03
A28: Jul | B28: 215594.06
A29: Aug | B29: 255159.91
A30: Sep | B30: 245911.29
A31: Oct | B31: 203420.53
A32: Nov | B32: 248307.71
A33: Dec | B33: 220765.1
A34: Grand Total | B34: 3586218.8

Sheet Order Analysis
A1: count order's | B1: Count of Order by mnoth
A2: Jan | B2: 197
A3: Feb | B3: 208
A4: Mar | B4: 190
A5: Apr | B5: 97
A6: May | B6: 92
A7: Jun | B7: 90
A8: Jul | B8: 108
A9: Aug | B9: 106
A10: Sep | B10: 106
A11: Oct | B11: 94
A12: Nov | B12: 105
A13: Dec | B13: 107
A14: Grand Total | B14: 1500
B23: Row Labels | C23: Sum of Revenue | D23: Count of Product
B24: Wireless Earbuds | C24: 3468185.2 | D24: 75
B25: Water Bottle | C25: 265097.95 | D25: 66
B26: Sunscreen | C26: 146897.65 | D26: 78
B27: Sports Shoes | C27: 144628.25 | D27: 49
B28: Socks Pack | C28: 237964 | D28: 69
B29: Smartwatch | C29: 2838978.7 | D29: 65
B30: Smartphone | C30: 2144681.8 | D30: 58
B31: Smart TV | C31: 2923156.6 | D31: 55
B32: Slim Fit Jeans | C32: 259345.75 | D32: 69
B33: Power Bank | C33: 2733564.9 | D33: 65
B34: Perfume | C34: 151620 | D34: 91
B35: Non-Stick Pan | C35: 294268.2 | D35: 62
... B47: Grand Total | C47: 20415050 | D47: 1500

Sheet Top_10 Revenue
A1: Row Labels | B1: Sum of Profit | C1: Sum of Revenue
A2: Wireless Earbuds | B2: 622732.38 | C2: 3468185.2
A3: Smart TV | B3: 544635.39 | C3: 2923156.6
A4: Smartwatch | B4: 487147.38 | C4: 2838978.7
A5: Power Bank | B5: 460228.22 | C5: 2733564.9
A6: Laptop | B6: 437719.66 | C6: 2630622.5
A7: Smartphone | B7: 399189.53 | C7: 2144681.8
A8: Air Fryer | B8: 53251.316 | C8: 305336.1
A9: Mixer Grinder | B9: 51694.889 | C9: 297233.75
A10: Non-Stick Pan | B10: 53722.295 | C10: 294268.2
A11: LED Bulb | B11: 50298.953 | C11: 288501.05
A12: Grand Total | B12: 3160620 | C12: 17924529
A21: Row Labels | B21: Sum of Revenue
A22: LED Bulb | B22: 288501.05
A23: Non-Stick Pan | B23: 294268.2
A24: Mixer Grinder | B24: 297233.75
A25: Air Fryer | B25: 305336.1
A26: Smartphone | B26: 2144681.8
A27: Laptop | B27: 2630622.5
A28: Power Bank | B28: 2733564.9
A29: Smartwatch | B29: 2838978.7
A30: Smart TV | B30: 2923156.6
A31: Wireless Earbuds | B31: 3468185.2
A32: Grand Total | B32: 17924529

Sheet Revenue Summary
A1: Row Labels | B1: Sum of Revenue
A2: Beauty & Grooming | B2: 669482.85
A3: Clothing & Fashion | B3: 1282144.3
A4: Electronics | B4: 16739190
A5: Home & Kitchen | B5: 1724233.3
A6: Grand Total | B6: 20415050
A19: Row Labels | B19: Sum of Revenue
A20: Asus | B20: 2630622.5
A21: Beardo | B21: 151620
A22: boAt | B22: 3468185.2
A23: Bombay Dyeing | B23: 273796.25
A24: Hawkins | B24: 294268.2
A25: Kent | B25: 305336.1
A26: L'Oreal | B26: 158199.25
A27: Levis | B27: 259345.75
A28: Mi | B28: 2733564.9
A29: Milton | B29: 265097.95
A30: Neutrogena | B30: 146897.65
A31: Nivea | B31: 115722.4
... A42: Grand Total | B42: 20415050

Sheet Average Summary
A1: customer name | B1: Average of Rating | C1: Sum of Revenue
A2: Yash Wardhan | B2: 4.0983607 | C2: 987490.6
A3: Sunil Gavaskar | B3: 3.96875 | C3: 1202643.2
A4: Sneha Reddy | B4: 3.71875 | C4: 913779.8
A5: Shilpa Shetty | B5: 3.9259259 | C5: 876876.9
A6: Sanjay Rao | B6: 3.9411765 | C6: 895619
A7: Rohan Das | B7: 4.0384615 | C7: 951539.8
A8: Pooja Nair | B8: 3.8461538 | C8: 880144.3
A9: Divya Dutta | B9: 4.0833333 | C9: 1264824.7
A10: Deepak Kumar | B10: 4.1129032 | C10: 1028778.8
A11: Aditi Rao | B11: 4.0149254 | C11: 1072427.3
A12: Grand Total | B12: 3.9761499 | C12: 10074124
A20: Row Labels | B20: Average of Rating
A21: Aditi Rao | B21: 4.0149254
A22: Arjun Choudhury | B22: 4.1272727
A23: Deepak Kumar | B23: 4.1129032
A24: Divya Dutta | B24: 4.0833333
A25: Jyoti Mishra | B25: 4.0961538
A26: Neha Gupta | B26: 4.0447761
A27: Rohan Das | B27: 4.0384615
A28: Vikram Singh | B28: 4.0142857
A29: Vivek Agnihotri | B29: 4.0545455
A30: Yash Wardhan | B30: 4.0983607
A31: Grand Total | B31: 4.0665557

Sheet KPI Summary
N2: Row Labels | O2: Count of Return Status
A3: Row Labels | B3: Count of Payment Mode | N3: No Return | O3: 1410
A4: Cash on Delivery (COD) | B4: 288 | N4: Not Applicable | O4: 55
A5: Credit Card | B5: 287 | N5: Returned | O5: 35
A6: Debit Card | B6: 299 | N6: Grand Total | O6: 1500
A7: Net Banking | B7: 307
A8: UPI | B8: 319
A9: Grand Total | B9: 1500
A17: Row Labels | B17: Count of Delivery Status
A18: Cancelled | B18: 55
A19: Delivered | B19: 1355
A20: Returned | B20: 35
A21: Shipped | B21: 55
A22: Grand Total | B22: 1500
N23: Row Labels | O23: Count of Seller
N24: IndiFlashMart | O24: 183
N25: OmniTechRetail | O25: 202
N26: RetailNet | O26: 384
N27: SaneRetails | O27: 177
N28: SuperComNet | O28: 188
N29: TrueComRetail | O29: 366
N30: Grand Total | O30: 1500
A40: Row Labels | B40: Sum of Revenue
A41: Gujarat | B41: 993050.4
A42: West Bengal | B42: 1079201.1
A43: Rajasthan | B43: 1215198.5
A44: Uttar Pradesh | B44: 1222993.1
A45: Tamil Nadu | B45: 1274288.5
A46: Punjab | B46: 1294748.4
A47: Telangana | B47: 1325238.9
A48: Karnataka | B48: 1422350.6
A49: Madhya Pradesh | B49: 1461531.5
A50: Bihar | B50: 1477911.6
A51: Kerala | B51: 1554327.6
A52: Assam | B52: 1581083.5
... A55: Grand Total | B55: 20415050
